LICENSE
MANIFEST.in
README.md
makefile
setup.cfg
setup.py
tox.ini
termui/__init__.py
termui/_compat.py
termui/_termui.py
termui/_termui_impl.py
termui/exceptions.py
termui/testing.py
termui/types.py
termui/utils.py
termui.egg-info/PKG-INFO
termui.egg-info/SOURCES.txt
termui.egg-info/dependency_links.txt
termui.egg-info/top_level.txt
tests/__init__.py
tests/conftest.py
tests/test_testing.py
tests/test_utils.py