Metadata-Version: 1.1
Name: termui
Version: 0.0.1-dev
Summary: Terminal interaction utiilities
Home-page: http://github.com/averagehuman/click-termui
Author: Gerard Flanagan
Author-email: gmflanagan@outlook.com
License: UNKNOWN
Platform: UNKNOWN
Classifier: License :: OSI Approved :: BSD License
Classifier: Programming Language :: Python
Classifier: Programming Language :: Python :: 3
